<list>
  <objects.Task>
    <id>35</id>
    <Description>Task#35</Description>
    <type>T</type>
    <type__id>1</type__id>
    <priority>2</priority>
    <resId>0</resId>
    <serviceTime>56</serviceTime>
    <node>
      <id>0</id>
      <latitude>378.1785669551941</latitude>
      <longitude>69.05121478825804</longitude>
    </node>
    <region>1</region>
    <timeint>
      <startTime>632</startTime>
      <endTime>1024</endTime>
    </timeint>
    <capacity>8.0</capacity>
  </objects.Task>
  <objects.Task>
    <id>36</id>
    <Description>Task#36</Description>
    <type>T</type>
    <type__id>1</type__id>
    <priority>1</priority>
    <resId>0</resId>
    <serviceTime>41</serviceTime>
    <node>
      <id>1</id>
      <latitude>337.3329643004873</latitude>
      <longitude>173.79518293914813</longitude>
    </node>
    <region>1</region>
    <timeint>
      <startTime>638</startTime>
      <endTime>908</endTime>
    </timeint>
    <capacity>3.0</capacity>
  </objects.Task>
  <objects.Task>
    <id>37</id>
    <Description>Task#37</Description>
    <type>T</type>
    <type__id>1</type__id>
    <priority>1</priority>
    <resId>0</resId>
    <serviceTime>37</serviceTime>
    <node>
      <id>2</id>
      <latitude>135.84066030742582</latitude>
      <longitude>102.84447350148012</longitude>
    </node>
    <region>1</region>
    <timeint>
      <startTime>703</startTime>
      <endTime>1033</endTime>
    </timeint>
    <capacity>7.0</capacity>
  </objects.Task>
  <objects.Task>
    <id>38</id>
    <Description>Task#38</Description>
    <type>T</type>
    <type__id>1</type__id>
    <priority>2</priority>
    <resId>0</resId>
    <serviceTime>40</serviceTime>
    <node>
      <id>3</id>
      <latitude>306.19221015424597</latitude>
      <longitude>247.40688423918084</longitude>
    </node>
    <region>1</region>
    <timeint>
      <startTime>655</startTime>
      <endTime>1136</endTime>
    </timeint>
    <capacity>5.0</capacity>
  </objects.Task>
  <objects.Task>
    <id>39</id>
    <Description>Task#39</Description>
    <type>T</type>
    <type__id>1</type__id>
    <priority>3</priority>
    <resId>0</resId>
    <serviceTime>63</serviceTime>
    <node>
      <id>4</id>
      <latitude>105.75251851562068</latitude>
      <longitude>492.49471577606226</longitude>
    </node>
    <region>1</region>
    <timeint>
      <startTime>567</startTime>
      <endTime>1059</endTime>
    </timeint>
    <capacity>8.0</capacity>
  </objects.Task>
  <objects.Task>
    <id>40</id>
    <Description>Task#40</Description>
    <type>T</type>
    <type__id>1</type__id>
    <priority>4</priority>
    <resId>0</resId>
    <serviceTime>77</serviceTime>
    <node>
      <id>5</id>
      <latitude>481.23714858491996</latitude>
      <longitude>234.90712204562237</longitude>
    </node>
    <region>1</region>
    <timeint>
      <startTime>556</startTime>
      <endTime>1064</endTime>
    </timeint>
    <capacity>3.0</capacity>
  </objects.Task>
  <objects.Task>
    <id>41</id>
    <Description>Task#41</Description>
    <type>T</type>
    <type__id>1</type__id>
    <priority>4</priority>
    <resId>0</resId>
    <serviceTime>72</serviceTime>
    <node>
      <id>6</id>
      <latitude>156.1784649232289</latitude>
      <longitude>342.40656743241635</longitude>
    </node>
    <region>1</region>
    <timeint>
      <startTime>508</startTime>
      <endTime>1005</endTime>
    </timeint>
    <capacity>9.0</capacity>
  </objects.Task>
  <objects.Task>
    <id>42</id>
    <Description>Task#42</Description>
    <type>T</type>
    <type__id>1</type__id>
    <priority>2</priority>
    <resId>0</resId>
    <serviceTime>51</serviceTime>
    <node>
      <id>7</id>
      <latitude>50.44200846029606</latitude>
      <longitude>112.12150231521223</longitude>
    </node>
    <region>1</region>
    <timeint>
      <startTime>545</startTime>
      <endTime>1045</endTime>
    </timeint>
    <capacity>5.0</capacity>
  </objects.Task>
  <objects.Task>
    <id>43</id>
    <Description>Task#43</Description>
    <type>T</type>
    <type__id>1</type__id>
    <priority>2</priority>
    <resId>0</resId>
    <serviceTime>84</serviceTime>
    <node>
      <id>8</id>
      <latitude>318.48100651008815</latitude>
      <longitude>493.1551493175086</longitude>
    </node>
    <region>1</region>
    <timeint>
      <startTime>522</startTime>
      <endTime>1107</endTime>
    </timeint>
    <capacity>4.0</capacity>
  </objects.Task>
  <objects.Task>
    <id>44</id>
    <Description>Task#44</Description>
    <type>T</type>
    <type__id>1</type__id>
    <priority>4</priority>
    <resId>0</resId>
    <serviceTime>73</serviceTime>
    <node>
      <id>9</id>
      <latitude>0.8332189839484472</latitude>
      <longitude>272.95833493404234</longitude>
    </node>
    <region>1</region>
    <timeint>
      <startTime>610</startTime>
      <endTime>984</endTime>
    </timeint>
    <capacity>9.0</capacity>
  </objects.Task>
  <objects.Task>
    <id>45</id>
    <Description>Task#45</Description>
    <type>T</type>
    <type__id>1</type__id>
    <priority>4</priority>
    <resId>0</resId>
    <serviceTime>74</serviceTime>
    <node>
      <id>10</id>
      <latitude>364.5474629787007</latitude>
      <longitude>160.49068568724218</longitude>
    </node>
    <region>1</region>
    <timeint>
      <startTime>704</startTime>
      <endTime>1243</endTime>
    </timeint>
    <capacity>1.0</capacity>
  </objects.Task>
  <objects.Task>
    <id>46</id>
    <Description>Task#46</Description>
    <type>T</type>
    <type__id>1</type__id>
    <priority>2</priority>
    <resId>0</resId>
    <serviceTime>54</serviceTime>
    <node>
      <id>11</id>
      <latitude>355.62707510233344</latitude>
      <longitude>179.37325937450737</longitude>
    </node>
    <region>1</region>
    <timeint>
      <startTime>544</startTime>
      <endTime>884</endTime>
    </timeint>
    <capacity>3.0</capacity>
  </objects.Task>
  <objects.Task>
    <id>47</id>
    <Description>Task#47</Description>
    <type>T</type>
    <type__id>1</type__id>
    <priority>4</priority>
    <resId>0</resId>
    <serviceTime>64</serviceTime>
    <node>
      <id>12</id>
      <latitude>241.6635229546177</latitude>
      <longitude>293.6578450990928</longitude>
    </node>
    <region>1</region>
    <timeint>
      <startTime>581</startTime>
      <endTime>933</endTime>
    </timeint>
    <capacity>8.0</capacity>
  </objects.Task>
  <objects.Task>
    <id>48</id>
    <Description>Task#48</Description>
    <type>T</type>
    <type__id>1</type__id>
    <priority>1</priority>
    <resId>0</resId>
    <serviceTime>74</serviceTime>
    <node>
      <id>13</id>
      <latitude>452.40939772800544</latitude>
      <longitude>481.92682459646795</longitude>
    </node>
    <region>1</region>
    <timeint>
      <startTime>665</startTime>
      <endTime>1069</endTime>
    </timeint>
    <capacity>2.0</capacity>
  </objects.Task>
  <objects.Task>
    <id>49</id>
    <Description>Task#49</Description>
    <type>T</type>
    <type__id>1</type__id>
    <priority>4</priority>
    <resId>0</resId>
    <serviceTime>87</serviceTime>
    <node>
      <id>14</id>
      <latitude>303.99030005150803</latitude>
      <longitude>349.83356882687673</longitude>
    </node>
    <region>1</region>
    <timeint>
      <startTime>640</startTime>
      <endTime>1145</endTime>
    </timeint>
    <capacity>4.0</capacity>
  </objects.Task>
</list>
